LICENSE
MANIFEST.in
README.md
requirements-dev.txt
requirements.txt
setup.py
examples/__init__.py
examples/example_in_readme.py
jycm/__init__.py
jycm/__main__.py
jycm/__version__.py
jycm/common.py
jycm/helper.py
jycm/jycm.py
jycm/km_matcher.py
jycm/operator.py
jycm/py.typed
jycm.egg-info/PKG-INFO
jycm.egg-info/SOURCES.txt
jycm.egg-info/dependency_links.txt
jycm.egg-info/requires.txt
jycm.egg-info/top_level.txt
jycm/jycm_viewer_assets/665.index.js
jycm/jycm_viewer_assets/665.index.js.LICENSE.txt
jycm/jycm_viewer_assets/ade705761eb7e702770d.ttf
jycm/jycm_viewer_assets/editor.worker.js
jycm/jycm_viewer_assets/index.js
jycm/jycm_viewer_assets/index.js.LICENSE.txt
jycm/jycm_viewer_assets/json.worker.js
jycm/jycm_viewer_assets/json.worker.js.LICENSE.txt