Metadata-Version: 2.1
Name: jycm
Version: 1.4.0
Summary: A highly flexible json diff framework for python.
Home-page: https://github.com/eggachecat/jycm
Author: eggachecat
Author-email: sunao_0626@hotmail.com
License: UNKNOWN
Keywords: json diff jsondiff operator flexible
Platform: UNKNOWN
Classifier: Intended Audience :: Developers
Classifier: Programming Language :: Python :: 3
Classifier: Programming Language :: Python :: 3.5
Requires-Python: !=3.0.*,!=3.1.*,!=3.2.*,!=3.3.*,!=3.4.*
Provides-Extra: dev
